disinter/__init__.py
disinter/api.py
disinter/command.py
disinter/components.py
disinter/context.py
disinter/disinter.py
disinter/errors.py
disinter/locales.py
disinter/response.py
disinter/types/__init__.py
disinter/types/api.py
disinter/types/channels.py
disinter/types/custom.py
disinter/types/etc.py
disinter/types/interaction.py
disinter/utils.py
disinter-0.0.1.dist-info/WHEEL
disinter-0.0.1.dist-info/METADATA
disinter-0.0.1.dist-info/RECORD
