Metadata-Version: 2.1
Name: disinter
Version: 0.0.1
Summary: A discord interactions library
Author: TheBoringDude
Author-email: iamcoderx@gmail.com
Requires-Python: >=3.10,<4.0
Classifier: Programming Language :: Python :: 3
Classifier: Programming Language :: Python :: 3.10
Classifier: Programming Language :: Python :: 3.11
Requires-Dist: discord-interactions (>=0.4.0,<0.5.0)
Requires-Dist: fastapi (>=0.85.1,<0.86.0)
Requires-Dist: requests (>=2.28.1,<3.0.0)
